galmoss/__init__.py
galmoss/data.py
galmoss/fitting.py
galmoss/uncertainty.py
galmoss/Parameter/__init__.py
galmoss/Parameter/basic.py
galmoss/Parameter/decorater.py
galmoss/profile/__init__.py
galmoss/profile/basic.py
galmoss/profile/light_profile.py
galmoss-20240216.6.dist-info/LICENSE
galmoss-20240216.6.dist-info/METADATA
galmoss-20240216.6.dist-info/WHEEL
galmoss-20240216.6.dist-info/top_level.txt
galmoss-20240216.6.dist-info/RECORD
