Metadata-Version: 2.1
Name: galmoss
Version: 20240216.6
Summary: A Python-based, Torch-powered tool for two-dimensional fitting of galaxy profiles. By seamlessly enabling GPU parallelization, GalMOSS meets the high computational demands of large-scale galaxy surveys.
Home-page: https://github.com/Chenmi0619/GALMoss
Author: Chen Mi
Author-email: chenmiastro@gmail.com
Keywords: Astronomy data analysis,Astronomy toolbox,Galaxy profile fitting
Classifier: Topic :: Scientific/Engineering
Classifier: License :: OSI Approved :: GNU Lesser General Public License v3 (LGPLv3)
Classifier: Programming Language :: Python :: 3
Requires-Python: >=3.9
License-File: LICENSE
